aichatlite/__init__.py
aichatlite/core/__init__.py
aichatlite/core/base.py
aichatlite/core/const.py
aichatlite/core/features/__init__.py
aichatlite/core/features/feature_main.py
aichatlite/core/features/handle_google_searchai.py
aichatlite/core/features/handle_pdf.py
aichatlite/core/omni_mixin.py
aichatlite/core/prompts.py
aichatlite/core/streamlit_app.py
aichatlite/core/streamlit_css.py
aichatlite/server_main.py
chat_gui.py
chat_run.py
claude_chat-0.1.1.dist-info/METADATA
claude_chat-0.1.1.dist-info/WHEEL
claude_chat-0.1.1.dist-info/entry_points.txt
claude_chat-0.1.1.dist-info/RECORD
