Metadata-Version: 2.1
Name: claude-chat
Version: 0.1.1
Summary: claude chat
Home-page: https://github.com/username/sa
License: GPL-3.0-or-later
Keywords: claude,claude_chat
Author: Kammari Santhosh
Requires-Python: >=3.10,<4.0
Classifier: License :: OSI Approved :: GNU General Public License v3 or later (GPLv3+)
Classifier: Programming Language :: Python :: 3
Classifier: Programming Language :: Python :: 3.10
Classifier: Programming Language :: Python :: 3.11
Classifier: Programming Language :: Python :: 3.12
Classifier: Programming Language :: Python :: 3.13
Project-URL: Repository, https://github.com/username/sa
